git_mirror/__about__.py
git_mirror/__init__.py
git_mirror/__main__.py
git_mirror/bug_report.py
git_mirror/check_cli_deps.py
git_mirror/cross_repo_sync.py
git_mirror/custom_types.py
git_mirror/dummies.py
git_mirror/features.py
git_mirror/file_system.py
git_mirror/logging_config.py
git_mirror/manage_config.py
git_mirror/manage_git.py
git_mirror/manage_github.py
git_mirror/manage_gitlab.py
git_mirror/manage_poetry.py
git_mirror/manage_pypi.py
git_mirror/menu.py
git_mirror/pat_init.py
git_mirror/pat_init_gitlab.py
git_mirror/performance.py
git_mirror/py.typed
git_mirror/router.py
git_mirror/safe_env.py
git_mirror/ui.py
git_mirror/version_check.py
git_mirror-0.3.8.dist-info/LICENSE
git_mirror-0.3.8.dist-info/METADATA
git_mirror-0.3.8.dist-info/WHEEL
git_mirror-0.3.8.dist-info/entry_points.txt
git_mirror-0.3.8.dist-info/RECORD
