Metadata-Version: 2.1
Name: git_mirror
Version: 0.3.8
Summary: Make your local git repos look like github or gitlab. See readme for how this differs from the many other multi-repo tools.
Home-page: https://github.com/matthewdeanmartin/git_mirror
License: MIT
Keywords: git,gitlab,github,polyrepo
Author: Matthew Martin
Author-email: matthewdeanmartin@gmail.com
Requires-Python: >=3.9
Classifier: Development Status :: 4 - Beta
Classifier: Intended Audience :: Developers
Classifier: License :: OSI Approved :: MIT License
Classifier: Operating System :: OS Independent
Classifier: Programming Language :: Python
Classifier: Programming Language :: Python :: 3
Classifier: Programming Language :: Python :: 3.9
Classifier: Programming Language :: Python :: 3.10
Classifier: Programming Language :: Python :: 3.11
Classifier: Programming Language :: Python :: 3.12
Classifier: Programming Language :: Python :: 3.8
Requires-Dist: GitPython (>=3.1.42)
Requires-Dist: PyGithub (>=2.2.0)
Requires-Dist: cli-tool-audit (>=3.0.1)
Requires-Dist: colorama (>=0.4.6,<1)
Requires-Dist: colorlog (>=6.8.0,<7)
Requires-Dist: httpx (>=0.26.0,<1)
Requires-Dist: inquirer (>=3.2.3,<4)
Requires-Dist: prettytable (==3.9.0)
Requires-Dist: python-dotenv (>=1.0.1,<2)
Requires-Dist: python-gitlab (>=4.4.0)
Requires-Dist: requests-cache (>=1.2.0,<2)
Requires-Dist: rich (>=13.7.0,<14)
Requires-Dist: termcolor
Requires-Dist: toml (>=0.10.2,<1)
Requires-Dist: tomlkit (>=0.12.3,<1)
Project-URL: Bug Tracker, https://github.com/matthewdeanmartin/git_mirror/issues
Project-URL: Change Log, https://github.com/matthewdeanmartin/git_mirror/blob/main/CHANGELOG.md
Project-URL: Documentation, https://matthewdeanmartin.github.io/git_mirror/git_mirror/index.html
Project-URL: Repository, https://github.com/matthewdeanmartin/git_mirror
